Install.txt
LGPL.txt
README.txt
__init__.py
authors.txt
changes.txt
ez_setup.py
faq.txt
license.txt
readme.txt
setup.py
thanks.txt
todo.txt
Behaviour.egg-info/PKG-INFO
Behaviour.egg-info/SOURCES.txt
Behaviour.egg-info/dependency_links.txt
Behaviour.egg-info/not-zip-safe
Behaviour.egg-info/requires.txt
Behaviour.egg-info/top_level.txt
example/machine/readme.txt
example/machine/Listing01/machine_spec.py
example/machine/Listing01/stdout.txt
example/machine/Listing02/machine.py
example/machine/Listing02/machine_spec.py
example/machine/Listing02/stdout.txt
example/machine/Listing03and04/machine.py
example/machine/Listing03and04/machine_spec.py
example/machine/Listing03and04/stdout.txt
example/machine/Listing05and06/machine.py
example/machine/Listing05and06/machine_spec.py
example/machine/Listing05and06/stdout.txt
example/machine/Listing07/machine.py
example/machine/Listing07/machine_spec.py
example/machine/Listing07/stdout.txt
example/machine/Listing08and09/machine.py
example/machine/Listing08and09/machine_spec.py
example/machine/Listing08and09/stdout.txt
example/machine/Listing10/machine.py
example/machine/Listing10/machine_spec.py
example/machine/Listing10/stdout.txt
example/machine/Listing11/machine.py
example/machine/Listing11/machine_spec.py
example/machine/Listing11/stdout.txt
example/machine/Listing12/machine.py
example/machine/Listing12/machine_spec.py
example/machine/Listing12/stdout.txt
example/machine/Listing13/machine.py
example/machine/Listing13/machine_spec.py
example/machine/Listing13/stdout.txt
example/machine/Listing14/machine.py
example/machine/Listing14/machine_spec.py
example/machine/Listing14/stdout.txt
example/machine/Listing15and16/machine.py
example/machine/Listing15and16/machine_spec.py
example/machine/Listing15and16/stdout.txt
example/machine/Listing17/machine.py
example/machine/Listing17/machine_spec.py
example/machine/Listing17/stdout.txt
example/machine/Listing18/machine.py
example/machine/Listing18/machine_spec.py
example/machine/Listing18/stdout.txt
example/machine/Listing19/machine.py
example/machine/Listing19/machine_spec.py
example/machine/Listing19/stdout.txt
example/machine/Listing20/machine.py
