Metadata-Version: 1.0
Name: Behaviour
Version: 0.1a4
Summary: Behaviour Driven Development in Python
Home-page: UNKNOWN
Author: Mark Dancer
Author-email: mark.dancer@pobox.com
License: UNKNOWN
Keywords: behaviour driven development design unit test testing unittest
Platform: UNKNOWN
Classifier: Development Status :: 3 - Alpha
Classifier: Environment :: Console
Classifier: Intended Audience :: Developers
Classifier: License :: OSI Approved :: GNU Library or Lesser General Public License (LGPL)
Classifier: Operating System :: OS Independent
Classifier: Operating System :: MacOS :: MacOS X
Classifier: Operating System :: Microsoft :: Windows
Classifier: Operating System :: Unix
Classifier: Programming Language :: Python
Classifier: Topic :: Software Development :: Testing
